rasgoql/__init__.py
rasgoql/errors.py
rasgoql/imports.py
rasgoql/main.py
rasgoql/version.py
rasgoql/data/__init__.py
rasgoql/data/base.py
rasgoql/data/bigquery.py
rasgoql/data/mysql.py
rasgoql/data/postgres.py
rasgoql/data/redshift.py
rasgoql/data/snowflake.py
rasgoql/data/sqlalchemy.py
rasgoql/primitives/__init__.py
rasgoql/primitives/enums.py
rasgoql/primitives/rendering.py
rasgoql/primitives/transforms.py
rasgoql/utils/__init__.py
rasgoql/utils/creds.py
rasgoql/utils/dbt.py
rasgoql/utils/decorators.py
rasgoql/utils/df.py
rasgoql/utils/messaging.py
rasgoql/utils/sql.py
rasgoql/utils/telemetry.py
rasgoql-1.6.4.dist-info/METADATA
rasgoql-1.6.4.dist-info/WHEEL
rasgoql-1.6.4.dist-info/top_level.txt
rasgoql-1.6.4.dist-info/RECORD
