Metadata-Version: 2.1
Name: rasgoql
Version: 1.6.4
Summary: Alpha version of rasgoQL open-source package.
Author: Rasgo Intelligence
Author-email: patrick@rasgoml.com
License: GNU Affero General Public License v3 or later (AGPLv3+)
Project-URL: Documentation, https://docs.rasgoql.com
Project-URL: Source, https://github.com/rasgointelligence/RasgoQL
Project-URL: Rasgo, https://www.rasgoml.com/
Project-URL: Changelog, https://github.com/rasgointelligence/RasgoQL/blob/main/rasgoql/CHANGELOG.md
Classifier: Development Status :: 3 - Alpha
Classifier: License :: OSI Approved :: GNU Affero General Public License v3 or later (AGPLv3+)
Classifier: Intended Audience :: Science/Research
Classifier: Intended Audience :: Developers
Classifier: Programming Language :: Python :: 3.7
Classifier: Programming Language :: Python :: 3.8
Classifier: Programming Language :: Python :: 3.9
Classifier: Programming Language :: Python :: 3.10
Classifier: Topic :: Database
Classifier: Topic :: Scientific/Engineering :: Information Analysis
Classifier: Topic :: Software Development :: Code Generators
Requires-Dist: jinja2
Requires-Dist: pandas
Requires-Dist: python-dotenv
Requires-Dist: pyyaml
Requires-Dist: rasgotransforms (~=1.3)
Requires-Dist: requests
Provides-Extra: bigquery
Requires-Dist: db-dtypes ; extra == 'bigquery'
Requires-Dist: google-auth-oauthlib ; extra == 'bigquery'
Requires-Dist: google-cloud-bigquery ; extra == 'bigquery'
Provides-Extra: mysql
Requires-Dist: pymysql ; extra == 'mysql'
Requires-Dist: SQLAlchemy ; extra == 'mysql'
Provides-Extra: postgres
Requires-Dist: psycopg2 ; extra == 'postgres'
Requires-Dist: SQLAlchemy ; extra == 'postgres'
Provides-Extra: redshift
Requires-Dist: redshift-connector (~=2.0) ; extra == 'redshift'
Requires-Dist: SQLAlchemy (~=1.4) ; extra == 'redshift'
Requires-Dist: sqlalchemy-redshift (~=0.8) ; extra == 'redshift'
Provides-Extra: snowflake
Requires-Dist: snowflake-connector-python ; extra == 'snowflake'
Requires-Dist: snowflake-connector-python[pandas] ; extra == 'snowflake'
